docs/conf.py
docs/create_roman_filters.rst
docs/create_simulated_catalog.rst
docs/index.rst
docs/installation.rst
docs/regtest_framework.rst
docs/roman_catalog_handler.rst
docs/roman_catalog_process.rst
docs/rtd_environment.yaml
docs/usage.rst
docs/_static/favicon.ico
examples/python_interface_1.py
examples/python_interface_2.py
examples/read_results_asdf_file.ipynb
roman_photoz/__init__.py
roman_photoz/__main__.py
roman_photoz/create_roman_filters.py
roman_photoz/create_simulated_catalog.py
roman_photoz/default_config_file.py
roman_photoz/logger.py
roman_photoz/roman_catalog_handler.py
roman_photoz/roman_catalog_process.py
roman_photoz/data/Roman_effarea_20210614.xlsx
roman_photoz/data/default_roman_output.para
roman_photoz/data/r00001_p_v01001001001001_270p65x49y70_f158_mbcat_cat.parquet
roman_photoz/data/roman_catalog_template.parquet
roman_photoz/regtest/README.md
roman_photoz/regtest/__init__.py
roman_photoz/regtest/conftest.py
roman_photoz/regtest/regtestdata.py
roman_photoz/regtest/test_integration.py
roman_photoz/tests/conftest.py
roman_photoz/tests/test_create_roman_filters.py
roman_photoz/tests/test_create_simulated_catalog.py
roman_photoz/tests/test_default_config_file.py
roman_photoz/tests/test_logger.py
roman_photoz/tests/test_roman_catalog_handler.py
roman_photoz/tests/test_roman_catalog_process.py
roman_photoz/utils/__init__.py
roman_photoz/utils/roman_photoz_utils.py
scripts/Makefile
scripts/create_asn_files_for_elp.sh
scripts/create_asn_files_for_mos.sh
scripts/create_asn_for_mbandcatalog.sh
scripts/create_skycell_asn.sh
scripts/make_cosmos_input_catalog.py
scripts/make_romanisim_input_catalog.py
scripts/notes.md
scripts/run_elp.sh
scripts/run_romanisim.sh
scripts/simulate_and_process_l1_files.sh
scripts/update_romanisim_catalog_fluxes.py
test-sdist/pyvenv.cfg
test-sdist/lib/python3.13/site-packages/pip/_vendor/vendor.txt
test-sdist/lib/python3.13/site-packages/pip-25.1.1.dist-info/licenses/AUTHORS.txt
test-sdist/lib/python3.13/site-packages/pip-25.1.1.dist-info/licenses/LICENSE.txt
test-sdist/lib64/python3.13/site-packages/pip/_vendor/vendor.txt
test-sdist/lib64/python3.13/site-packages/pip-25.1.1.dist-info/licenses/AUTHORS.txt
test-sdist/lib64/python3.13/site-packages/pip-25.1.1.dist-info/licenses/LICENSE.txt
roman_photoz-0.1.0.dist-info/METADATA
roman_photoz-0.1.0.dist-info/WHEEL
roman_photoz-0.1.0.dist-info/entry_points.txt
roman_photoz-0.1.0.dist-info/top_level.txt
test-sdist/lib/python3.13/site-packages/pip-25.1.1.dist-info/entry_points.txt
test-sdist/lib/python3.13/site-packages/pip-25.1.1.dist-info/top_level.txt
test-sdist/lib64/python3.13/site-packages/pip-25.1.1.dist-info/entry_points.txt
test-sdist/lib64/python3.13/site-packages/pip-25.1.1.dist-info/top_level.txt
roman_photoz-0.1.0.dist-info/RECORD
